CHANGELOG.txt
LICENCE.txt
MANIFEST.in
README.txt
setup.py
tpy_CDCN/__init__.py
tpy_CDCN/check.py
tpy_CDCN.egg-info/PKG-INFO
tpy_CDCN.egg-info/SOURCES.txt
tpy_CDCN.egg-info/dependency_links.txt
tpy_CDCN.egg-info/requires.txt
tpy_CDCN.egg-info/top_level.txt