Metadata-Version: 2.1
Name: tpy-CDCN
Version: 1.0.0
Summary: A very basic calculator
Home-page: 
Author: Nghia Pham
Author-email: ngph01012k1@gmail.com
License: MIT
Keywords: calculator
Classifier: Development Status :: 5 - Production/Stable
Classifier: Intended Audience :: Education
Classifier: Operating System :: Microsoft :: Windows :: Windows 10
Classifier: License :: OSI Approved :: MIT License
Classifier: Programming Language :: Python :: 3
License-File: LICENCE.txt
